package_image_processing_DiO/__init__.py
package_image_processing_DiO/processing/__init__.py
package_image_processing_DiO/processing/combination.py
package_image_processing_DiO/processing/transformation.py
package_image_processing_DiO/utils/__init__.py
package_image_processing_DiO/utils/io.py
package_image_processing_DiO/utils/plot.py
package_image_processing_DiO-0.0.2.dist-info/METADATA
package_image_processing_DiO-0.0.2.dist-info/WHEEL
package_image_processing_DiO-0.0.2.dist-info/top_level.txt
package_image_processing_DiO-0.0.2.dist-info/RECORD
