Metadata-Version: 2.1
Name: package-image-processing-DiO
Version: 0.0.2
Summary: Test version Image processing package using skimage. This project belongs to Karina Tiemi Kato.
Home-page: https://github.com/JonathanCristovao/Bootcamp-Unimed-BH-Ciencia-de-Dados-DiO/tree/main/python-para-cientista-de-dados/package_image_processing
Author: jonathansilva13
Author-email: jonathancristovao13@gmail.com
Requires-Python: >=3.5
Requires-Dist: matplotlib
Requires-Dist: numpy
Requires-Dist: scikit-image (>=0.16.1)
